[
    {
	"name": "getFolderContents",
	"inputs": ["f",["/home/adam/ownCloud/PC/conkyInputs/"],"localhost"],
	"loop": "file",
	"response": [
            {
		"name": "moveFile",
		"inputs": ["file", ["localhost","localhost"], ["/home/adam/ownCloud/PC/conkyInputs/", "tempFolder"], "adam"]
            }
	]
    },
    {
	"name":"ownQuant",
	"inputs":["tempFolder"]
    },
    {
	"name": "getMatchContents",
	"inputs": ["f", "false", "false", "false", ["tempFolder"], "localhost", ["OUT","ALL","graph"]],
	"loop": "file",
	"response": [
            {
		"name": "moveFile",
		"inputs": ["file", ["localhost","localhost"], ["tempFolder", "/home/adam/quantTest"], "adam"]
            }
	]
    }
]
